README.md
setup.py
src/nose_summary_report/__init__.py
src/nose_summary_report.egg-info/PKG-INFO
src/nose_summary_report.egg-info/SOURCES.txt
src/nose_summary_report.egg-info/dependency_links.txt
src/nose_summary_report.egg-info/entry_points.txt
src/nose_summary_report.egg-info/pbr.json
src/nose_summary_report.egg-info/requires.txt
src/nose_summary_report.egg-info/top_level.txt