Metadata-Version: 2.1
Name: nose-summary-report
Version: 1.0.3
Summary: Nose plugin that generates a final summary of tests status as a table
Home-page: https://github.com/Lucas-C/nose-summary-report
Author: Lucas Cimon
Author-email: lucas.cimon+nose-summary-report@gmail.com
License: GNU LGPL
Platform: UNKNOWN
Classifier: Development Status :: 5 - Production/Stable
Classifier: Intended Audience :: Developers
Classifier: License :: OSI Approved :: BSD License
Classifier: Operating System :: Unix
Classifier: Operating System :: POSIX
Classifier: Operating System :: Microsoft :: Windows
Classifier: Programming Language :: Python
Classifier: Programming Language :: Python :: 2
Classifier: Programming Language :: Python :: 2.7
Classifier: Programming Language :: Python :: 3
Classifier: Programming Language :: Python :: 3.7
Classifier: Programming Language :: Python :: Implementation :: CPython
Classifier: Programming Language :: Python :: Implementation :: PyPy
Classifier: Topic :: Utilities
